vecgl/__init__.py
vecgl/_version.py
vecgl/bb3tree.py
vecgl/export.py
vecgl/linalg.py
vecgl/model.py
vecgl/modellib.py
vecgl/rendering.py
vecgl/transforms.py
vecgl/viewer.py
vecgl-0.0.5.dist-info/LICENSE
vecgl-0.0.5.dist-info/METADATA
vecgl-0.0.5.dist-info/WHEEL
vecgl-0.0.5.dist-info/top_level.txt
vecgl-0.0.5.dist-info/RECORD
