Metadata-Version: 2.1
Name: vecgl
Version: 0.0.5
Summary: VecGL is a 3D rendering engine with vector output
Author-email: Frederik Gossen <frederik.gossen@gmail.com>
License: Copyright 2022 Frederik Gossen
Keywords: rendering,rendering engine,3D engine,vector graphics,graphics library,3D
Classifier: Programming Language :: Python :: 3
Classifier: License :: OSI Approved :: MIT License
Classifier: Operating System :: OS Independent
Classifier: Topic :: Multimedia :: Graphics :: 3D Rendering
Requires-Python: >=3.7
License-File: LICENSE
